Metadata-Version: 2.1
Name: mapexcept
Version: 1.0.0
Summary: Exception? Just keep mapping.
Home-page: UNKNOWN
Author: Perzan
Author-email: PerzanDevelopment@gmail.com
License: UNKNOWN
Platform: UNKNOWN
